foss4fus/__init__.py
foss4fus/ccf_v3_atlas_generation.py
foss4fus/clustering.py
foss4fus/correlation_analysis.py
foss4fus/data_loading.py
foss4fus/features_extraction.py
foss4fus/quality_control.py
foss4fus/quantification.py
foss4fus/region_averaging_analysis.py
foss4fus/registration.py
foss4fus/utils.py
foss4fus/atlases/__init__.py
foss4fus/atlases/__pycache__/__init__.cpython-39.pyc
foss4fus/atlases/atlases_lists/__init__.py
foss4fus/atlases/atlases_lists/regions_ccf_v3_100_nolayersnoparts.txt
foss4fus/atlases/atlases_lists/__pycache__/__init__.cpython-39.pyc
foss4fus/atlases/atlases_npy/__init__.py
foss4fus/atlases/atlases_npy/atlas_ccf_v3_100_contours.npy
foss4fus/atlases/atlases_npy/atlas_ccf_v3_100_nolayersnoparts.npy
foss4fus/atlases/atlases_npy/__pycache__/__init__.cpython-39.pyc
foss4fus-0.1.3.dist-info/METADATA
foss4fus-0.1.3.dist-info/WHEEL
foss4fus-0.1.3.dist-info/top_level.txt
foss4fus-0.1.3.dist-info/RECORD
